alchemysession/__init__.py
alchemysession/core.py
alchemysession/core_postgres.py
alchemysession/orm.py
alchemysession/sqlalchemy.py
sqlalchemy_telethon_session-0.0.1.dist-info/LICENSE
sqlalchemy_telethon_session-0.0.1.dist-info/METADATA
sqlalchemy_telethon_session-0.0.1.dist-info/WHEEL
sqlalchemy_telethon_session-0.0.1.dist-info/top_level.txt
sqlalchemy_telethon_session-0.0.1.dist-info/RECORD
