Metadata-Version: 2.1
Name: sqlalchemy-telethon-session
Version: 0.0.1
Summary: SQLAlchemy backend for Telethon session storage
Home-page: https://github.com/AI-Stratov/telethon-session-sqlalchemy
Author: Tulir Asokan
Author-email: tulir@maunium.net
Classifier: Development Status :: 4 - Beta
Classifier: License :: OSI Approved :: MIT License
Classifier: Programming Language :: Python
Classifier: Programming Language :: Python :: 3
Classifier: Programming Language :: Python :: 3.6
Classifier: Programming Language :: Python :: 3.7
Classifier: Programming Language :: Python :: 3.8
Classifier: Programming Language :: Python :: 3.9
Classifier: Programming Language :: Python :: 3.10
Requires-Python: ~=3.5
License-File: LICENSE
Requires-Dist: SQLAlchemy >=2
